gz_base.cpython-39-darwin.so
gz_base-1.0.3.dist-info/RECORD
gz_base-1.0.3.dist-info/LICENSE
gz_base-1.0.3.dist-info/WHEEL
gz_base-1.0.3.dist-info/top_level.txt
gz_base-1.0.3.dist-info/METADATA
